caf/toolkit/__init__.py
caf/toolkit/__main__.py
caf/toolkit/_version.py
caf/toolkit/arguments.py
caf/toolkit/config_base.py
caf/toolkit/cost_utils.py
caf/toolkit/io.py
caf/toolkit/log_helpers.py
caf/toolkit/math_utils.py
caf/toolkit/py.typed
caf/toolkit/timing.py
caf/toolkit/toolbox.py
caf/toolkit/tqdm_utils.py
caf/toolkit/translation.py
caf/toolkit/validators.py
caf/toolkit/concurrency/__init__.py
caf/toolkit/concurrency/multiprocessing_wrapper.py
caf/toolkit/core/__init__.py
caf/toolkit/core/types.py
caf/toolkit/pandas_utils/__init__.py
caf/toolkit/pandas_utils/df_handling.py
caf/toolkit/pandas_utils/matrices.py
caf/toolkit/pandas_utils/numpy_conversions.py
caf/toolkit/pandas_utils/random.py
caf/toolkit/pandas_utils/utility.py
caf/toolkit/pandas_utils/wide_df_handling.py
caf_toolkit-0.11.0.dist-info/licenses/LICENSE
caf_toolkit-0.11.0.dist-info/METADATA
caf_toolkit-0.11.0.dist-info/WHEEL
caf_toolkit-0.11.0.dist-info/entry_points.txt
caf_toolkit-0.11.0.dist-info/top_level.txt
caf_toolkit-0.11.0.dist-info/RECORD
