Metadata-Version: 2.4
Name: caf.toolkit
Version: 0.11.0
Summary: A toolkit of transport planning and appraisal functionalities
Author: Transport for the North
License: Copyright © Transport for the North (“TfN”) (2023).
Project-URL: Bug Tracker, https://github.com/Transport-for-the-North/caf.toolkit/issues
Project-URL: Homepage, https://github.com/Transport-for-the-North/caf.toolkit
Project-URL: Source, https://github.com/Transport-for-the-North/caf.toolkit
Project-URL: Documentation, http://caftoolkit.rtfd.io/
Classifier: Programming Language :: Python :: 3 :: Only
Classifier: Programming Language :: Python :: 3.10
Classifier: Programming Language :: Python :: 3.11
Classifier: Programming Language :: Python :: 3.12
Classifier: Programming Language :: Python :: 3.13
Requires-Python: >=3.10
License-File: LICENSE
Requires-Dist: numpy>=1.19.0
Requires-Dist: pandas>=2.0.0
Requires-Dist: tqdm>=4.50.2
Requires-Dist: pydantic>=2.5.0
Requires-Dist: strictyaml>=1.6
Requires-Dist: psutil>=5.9.0
Provides-Extra: dev
Requires-Dist: setuptools>=64.0.0; extra == "dev"
Requires-Dist: black>=24.1.1; extra == "dev"
Requires-Dist: isort>=5.12.0; extra == "dev"
Requires-Dist: mypy>=1.0.0; extra == "dev"
Requires-Dist: mypy_extensions>=1.0.0; extra == "dev"
Requires-Dist: pydocstyle[toml]>=6.1.1; extra == "dev"
Requires-Dist: pylint>=3.3.1; extra == "dev"
Requires-Dist: pandas-stubs>=2.0.0; extra == "dev"
Requires-Dist: pytest>=7.4.0; extra == "dev"
Requires-Dist: pytest-cov>=4.1.0; extra == "dev"
Requires-Dist: pytest-xdist>=3.3.1; extra == "dev"
Requires-Dist: tox>=3.24.3; extra == "dev"
Requires-Dist: openpyxl>=3.1.5; extra == "dev"
Requires-Dist: versioningit>=2.2.0; extra == "dev"
Provides-Extra: docs
Requires-Dist: sphinx>=7.1.2; extra == "docs"
Requires-Dist: pydata-sphinx-theme>=0.14.1; extra == "docs"
Requires-Dist: graphviz>=0.20.1; extra == "docs"
Requires-Dist: sphinx-gallery>=0.17.1; extra == "docs"
Requires-Dist: matplotlib; extra == "docs"
Requires-Dist: sphinx-argparse>=0.5.2; extra == "docs"
Provides-Extra: sparse
Requires-Dist: sparse>=0.15.4; extra == "sparse"
Dynamic: license-file
